romgeo/__init__.py
romgeo/crs.py
romgeo/projections.py
romgeo/transformations.py
romgeo/cuda/__init__.py
romgeo/cuda/projections.py
romgeo/cuda/transformations.py
romgeo-0.1.5.dist-info/licenses/LICENSE
romgeo-0.1.5.dist-info/METADATA
romgeo-0.1.5.dist-info/WHEEL
romgeo-0.1.5.dist-info/top_level.txt
romgeo-0.1.5.dist-info/RECORD
