Metadata-Version: 2.4
Name: romgeo
Version: 0.1.5
Summary: RomGEO Geospatial Utilities for Romania
Home-page: https://github.com/cartografie-ro/romgeo/
Author: Mihail-Alexandru CRETU
Author-email: romgeo@cartografie.ro
Classifier: Programming Language :: Python :: 3
Classifier: Operating System :: OS Independent
Requires-Python: >=3.8
License-File: LICENSE
Requires-Dist: numba
Requires-Dist: numpy
Requires-Dist: pyproj
Dynamic: license-file
